MANIFEST.in
README.md
setup.py
p2p0mq/__init__.py
p2p0mq/__version__.py
p2p0mq/constants.py
p2p0mq/errors.py
p2p0mq/message.py
p2p0mq/overrides.py
p2p0mq/peer.py
p2p0mq.egg-info/PKG-INFO
p2p0mq.egg-info/SOURCES.txt
p2p0mq.egg-info/dependency_links.txt
p2p0mq.egg-info/requires.txt
p2p0mq.egg-info/top_level.txt
p2p0mq/app/__init__.py
p2p0mq/app/base.py
p2p0mq/app/client.py
p2p0mq/app/server.py
p2p0mq/app/theapp.py
p2p0mq/concerns/__init__.py
p2p0mq/concerns/ask_around.py
p2p0mq/concerns/base.py
p2p0mq/concerns/connector.py
p2p0mq/concerns/heart_beat.py
p2p0mq/concerns/manager.py
p2p0mq/db/__init__.py
p2p0mq/db/peer_store.py
p2p0mq/message_queue/__init__.py
p2p0mq/message_queue/base.py
p2p0mq/message_queue/fast.py
p2p0mq/message_queue/medium.py
p2p0mq/message_queue/slow.py
p2p0mq/router/__init__.py
p2p0mq/security/__init__.py
p2p0mq/utils/__init__.py
p2p0mq/utils/lang.py
p2p0mq/utils/thread/__init__.py
p2p0mq/utils/thread/koloopthread.py
p2p0mq/utils/thread/kothread.py
p2p0mq/utils/thread/netthread.py